MANIFEST.in
README
requirements.txt
setup.py
pymqi/CMQC.py
pymqi/CMQCFC.py
pymqi/CMQXC.py
pymqi/CMQZC.py
pymqi/__init__.py
pymqi/pymqe.c
pymqi.egg-info/PKG-INFO
pymqi.egg-info/SOURCES.txt
pymqi.egg-info/dependency_links.txt
pymqi.egg-info/top_level.txt