Metadata-Version: 1.1
Name: pymqi
Version: 1.7.2.post1
Summary: Python IBM MQI Extension for IBM MQ (formerly WebSphere MQ and MQSeries).
Home-page: https://dsuch.github.io/pymqi/
Author: Dariusz Suchojad
Author-email: pymqi@m.zato.io
License: Python Software Foundation License
Download-URL: https://pypi.python.org/pypi/pymqi
Keywords: pymqi OBM WebSphere MQ WMQ MQSeries IBM middleware messaging queueing asynchronous SOA EAI ESB integration
Platform: OS Independent
Classifier: Development Status :: 5 - Production/Stable
Classifier: License :: OSI Approved :: Python Software Foundation License
Classifier: Intended Audience :: Developers
Classifier: Natural Language :: English
Classifier: Operating System :: OS Independent
Classifier: Programming Language :: C
Classifier: Programming Language :: Python
Classifier: Topic :: Software Development :: Libraries :: Python Modules
Classifier: Topic :: Software Development :: Object Brokering
